click_completion_helper/__init__.py
click_completion_helper/data/bash
click_completion_helper-0.0.3.dist-info/LICENSE
click_completion_helper-0.0.3.dist-info/METADATA
click_completion_helper-0.0.3.dist-info/WHEEL
click_completion_helper-0.0.3.dist-info/entry_points.txt
click_completion_helper-0.0.3.dist-info/top_level.txt
click_completion_helper-0.0.3.dist-info/RECORD
